easygcpz/__init__.py
easygcpz/main.py
EasyGCPz-0.1.1.dist-info/License
EasyGCPz-0.1.1.dist-info/METADATA
EasyGCPz-0.1.1.dist-info/WHEEL
EasyGCPz-0.1.1.dist-info/top_level.txt
EasyGCPz-0.1.1.dist-info/RECORD
