Metadata-Version: 2.1
Name: EasyGCPz
Version: 0.1.1
Home-page: https://github.com/mw-os/EasyGCPz
Author: Mitchell Williams
License-File: License
Requires-Dist: google.cloud
